{
    "slidergithub": [
        {
            "title": "Loading Screen",
            "description": "With a modern and beautiful design, you can do things such as authorities, server information, music status, game play, and make your server unique.",
            "image": "https://cdn.discordapp.com/attachments/1058551951241007144/1058766522094452826/image.png",
            "url": "https://debux.tebex.io/package/5448328"
        },
        {
            "title": "Announce Script",
            "description": "A unique script with a modern design, you can permanently announce important events on your server to players and attract attention.",
            "image": "https://media.discordapp.net/attachments/1031244059186053220/1031640355101233152/unknown.png?width=1700&height=916",
            "url": "https://debux.tebex.io/package/5342218"
        },
          {
            "title": "Scratch Lottery",
            "description": "A scratch system for your server, you can add it to your server and generate revenue by adding donate or you can entertain players by adding it to the market.",
            "image": "https://media.discordapp.net/attachments/1093578197326639154/1093612891338453112/image.png?width=1229&height=691",
            "url": "https://debux.tebex.io/package/5618112"
        }
    ]
}
